README.md
setup.py
buco_db_manager.egg-info/PKG-INFO
buco_db_manager.egg-info/SOURCES.txt
buco_db_manager.egg-info/dependency_links.txt
buco_db_manager.egg-info/requires.txt
buco_db_manager.egg-info/top_level.txt
src/__init__.py
src/models/__init__.py
src/models/fixture.py
src/models/fixture_stats.py
src/models/injury.py
src/models/league.py
src/models/lineups.py
src/models/odds.py
src/models/team.py
src/models/team_fixture_stats.py
src/models/team_lineups.py
src/models/team_ratings.py
src/models/team_stats.py
src/models/xgoals.py
src/mongo_db/__init__.py
src/mongo_db/mongo_db.py
src/mongo_db/mongo_db_repository.py
src/repositories/__init__.py
src/repositories/fixture_repository.py
src/repositories/fixture_stats_repository.py
src/repositories/injury_repository.py
src/repositories/lineups_repository.py
src/repositories/odds_repository.py
src/repositories/team_ratings_repository.py
src/repositories/team_repository.py
src/repositories/team_stats_repository.py
src/repositories/xgoals_repository.py
src/services/__init__.py
src/services/fixture_service.py
src/services/fixture_stats_service.py
src/services/injury_service.py
src/services/lineups_service.py
src/services/odds_service.py
src/services/team_ratings_service.py
src/services/team_service.py
src/services/team_stats_service.py
src/services/xgoals_service.py