Metadata-Version: 2.1
Name: buco_db_manager
Version: 0.1
Requires-Dist: PyYAML
Requires-Dist: RapidFuzz
Requires-Dist: pymongo
Requires-Dist: dnspython
Requires-Dist: Unidecode
